{"mentionMatched":"gala","articleId":"33501086722","companyId":"6005663","articleLength":5172,"countOfDistinctIndustry":15,"countOfOccurence":3,"countOfOccurenceOfAliases":3,"countOfOccurenceOfNamePreserveList":3,"countOfSignificantStrings":3,"countOfUrlMatch":0,"countryMatchByOverlapScore":0.5,"directCityMatchScore":0.0,"directCountryMatchScore":0.6,"directStateMatchScore":0.0,"exactMatch":true,"fieldMatch":3,"isCommon":false,"isIndustry":true,"isProminent":false,"isProminentByItself":false,"isProminentByParent":false,"isTickerMatch":false,"isUrlMatched":false,"personScore":-1000.0,"stateMatchByOverlapScore":0.0,"sumOfIndustry":43,"w2vScore":0.0,"isGold":0,"isSingleCompany":false}
{"mentionMatched":"gala","articleId":"33501086722","companyId":"16523473","articleLength":5172,"countOfDistinctIndustry":1,"countOfOccurence":3,"countOfOccurenceOfAliases":3,"countOfOccurenceOfNamePreserveList":3,"countOfSignificantStrings":3,"countOfUrlMatch":0,"countryMatchByOverlapScore":0.0,"directCityMatchScore":-1000.0,"directCountryMatchScore":0.0,"directStateMatchScore":-1000.0,"exactMatch":false,"fieldMatch":2,"isCommon":false,"isIndustry":true,"isProminent":false,"isProminentByItself":true,"isProminentByParent":false,"isTickerMatch":false,"isUrlMatched":false,"personScore":0.0,"stateMatchByOverlapScore":-1000.0,"sumOfIndustry":2,"w2vScore":9.551909206076633,"isGold":0,"isSingleCompany":false}
{"mentionMatched":"gala","articleId":"33501086722","companyId":"5201840","articleLength":5172,"countOfDistinctIndustry":10,"countOfOccurence":3,"countOfOccurenceOfAliases":3,"countOfOccurenceOfNamePreserveList":3,"countOfSignificantStrings":3,"countOfUrlMatch":0,"countryMatchByOverlapScore":0.5,"directCityMatchScore":0.0,"directCountryMatchScore":0.6,"directStateMatchScore":0.0,"exactMatch":false,"fieldMatch":2,"isCommon":false,"isIndustry":true,"isProminent":false,"isProminentByItself":false,"isProminentByParent":false,"isTickerMatch":false,"isUrlMatched":false,"personScore":-1000.0,"stateMatchByOverlapScore":0.0,"sumOfIndustry":17,"w2vScore":1.9412081776716696,"isGold":0,"isSingleCompany":false}
{"mentionMatched":"gala","articleId":"33501086722","companyId":"819703","articleLength":5172,"countOfDistinctIndustry":5,"countOfOccurence":3,"countOfOccurenceOfAliases":3,"countOfOccurenceOfNamePreserveList":3,"countOfSignificantStrings":3,"countOfUrlMatch":0,"countryMatchByOverlapScore":0.0,"directCityMatchScore":0.0,"directCountryMatchScore":0.0,"directStateMatchScore":0.0,"exactMatch":false,"fieldMatch":2,"isCommon":false,"isIndustry":true,"isProminent":false,"isProminentByItself":false,"isProminentByParent":false,"isTickerMatch":false,"isUrlMatched":false,"personScore":0.0,"stateMatchByOverlapScore":0.0,"sumOfIndustry":10,"w2vScore":2.200759881080056,"isGold":0,"isSingleCompany":false}
{"mentionMatched":"gala","articleId":"33501086722","companyId":"7538148","articleLength":5172,"countOfDistinctIndustry":10,"countOfOccurence":3,"countOfOccurenceOfAliases":3,"countOfOccurenceOfNamePreserveList":3,"countOfSignificantStrings":3,"countOfUrlMatch":0,"countryMatchByOverlapScore":0.5,"directCityMatchScore":0.0,"directCountryMatchScore":0.6,"directStateMatchScore":0.0,"exactMatch":false,"fieldMatch":2,"isCommon":false,"isIndustry":true,"isProminent":false,"isProminentByItself":false,"isProminentByParent":false,"isTickerMatch":false,"isUrlMatched":false,"personScore":-1000.0,"stateMatchByOverlapScore":0.0,"sumOfIndustry":17,"w2vScore":4.293960640415589,"isGold":0,"isSingleCompany":false}
{"mentionMatched":"gala","articleId":"33501086722","companyId":"2481252","articleLength":5172,"countOfDistinctIndustry":13,"countOfOccurence":3,"countOfOccurenceOfAliases":3,"countOfOccurenceOfNamePreserveList":3,"countOfSignificantStrings":3,"countOfUrlMatch":0,"countryMatchByOverlapScore":0.5,"directCityMatchScore":0.0,"directCountryMatchScore":0.6,"directStateMatchScore":0.0,"exactMatch":false,"fieldMatch":2,"isCommon":false,"isIndustry":true,"isProminent":false,"isProminentByItself":false,"isProminentByParent":false,"isTickerMatch":false,"isUrlMatched":false,"personScore":0.0,"stateMatchByOverlapScore":0.0,"sumOfIndustry":44,"w2vScore":0.0,"isGold":0,"isSingleCompany":false}
{"mentionMatched":"gala","articleId":"33501086722","companyId":"7709811","articleLength":5172,"countOfDistinctIndustry":10,"countOfOccurence":3,"countOfOccurenceOfAliases":3,"countOfOccurenceOfNamePreserveList":3,"countOfSignificantStrings":3,"countOfUrlMatch":0,"countryMatchByOverlapScore":0.5,"directCityMatchScore":0.0,"directCountryMatchScore":0.6,"directStateMatchScore":0.0,"exactMatch":true,"fieldMatch":3,"isCommon":false,"isIndustry":true,"isProminent":false,"isProminentByItself":false,"isProminentByParent":false,"isTickerMatch":false,"isUrlMatched":false,"personScore":-1000.0,"stateMatchByOverlapScore":0.0,"sumOfIndustry":17,"w2vScore":0.0,"isGold":0,"isSingleCompany":false}
{"mentionMatched":"gala","articleId":"33501086722","companyId":"3589677","articleLength":5172,"countOfDistinctIndustry":0,"countOfOccurence":3,"countOfOccurenceOfAliases":3,"countOfOccurenceOfNamePreserveList":0,"countOfSignificantStrings":0,"countOfUrlMatch":0,"countryMatchByOverlapScore":0.0,"directCityMatchScore":-1000.0,"directCountryMatchScore":0.0,"directStateMatchScore":-1000.0,"exactMatch":false,"fieldMatch":2,"isCommon":false,"isIndustry":true,"isProminent":false,"isProminentByItself":false,"isProminentByParent":false,"isTickerMatch":false,"isUrlMatched":false,"personScore":-1000.0,"stateMatchByOverlapScore":-1000.0,"sumOfIndustry":0,"w2vScore":14.977393635128161,"isGold":0,"isSingleCompany":false}
{"mentionMatched":"gala","articleId":"33501086722","companyId":"8262019","articleLength":5172,"countOfDistinctIndustry":3,"countOfOccurence":3,"countOfOccurenceOfAliases":3,"countOfOccurenceOfNamePreserveList":3,"countOfSignificantStrings":3,"countOfUrlMatch":0,"countryMatchByOverlapScore":0.5,"directCityMatchScore":0.0,"directCountryMatchScore":0.6,"directStateMatchScore":0.0,"exactMatch":true,"fieldMatch":3,"isCommon":false,"isIndustry":true,"isProminent":false,"isProminentByItself":false,"isProminentByParent":false,"isTickerMatch":false,"isUrlMatched":false,"personScore":-1000.0,"stateMatchByOverlapScore":0.0,"sumOfIndustry":4,"w2vScore":0.0,"isGold":0,"isSingleCompany":false}
{"mentionMatched":"gala","articleId":"33501086722","companyId":"1178168","articleLength":5172,"countOfDistinctIndustry":13,"countOfOccurence":3,"countOfOccurenceOfAliases":3,"countOfOccurenceOfNamePreserveList":3,"countOfSignificantStrings":3,"countOfUrlMatch":0,"countryMatchByOverlapScore":0.0,"directCityMatchScore":0.0,"directCountryMatchScore":0.0,"directStateMatchScore":0.0,"exactMatch":false,"fieldMatch":2,"isCommon":false,"isIndustry":true,"isProminent":false,"isProminentByItself":false,"isProminentByParent":false,"isTickerMatch":false,"isUrlMatched":false,"personScore":-1000.0,"stateMatchByOverlapScore":0.0,"sumOfIndustry":44,"w2vScore":13.128144012831727,"isGold":0,"isSingleCompany":false}
{"mentionMatched":"daimler","articleId":"33546918980","companyId":"18742047","articleLength":6032,"countOfDistinctIndustry":0,"countOfOccurence":1,"countOfOccurenceOfAliases":1,"countOfOccurenceOfNamePreserveList":1,"countOfSignificantStrings":1,"countOfUrlMatch":0,"countryMatchByOverlapScore":0.0,"directCityMatchScore":0.0,"directCountryMatchScore":0.0,"directStateMatchScore":-1000.0,"exactMatch":false,"fieldMatch":2,"isCommon":false,"isIndustry":false,"isProminent":false,"isProminentByItself":false,"isProminentByParent":false,"isTickerMatch":true,"isUrlMatched":false,"personScore":-1000.0,"stateMatchByOverlapScore":-1000.0,"sumOfIndustry":0,"w2vScore":0.0,"isGold":0,"isSingleCompany":false}
{"mentionMatched":"daimler","articleId":"33546918980","companyId":"51380418","articleLength":6032,"countOfDistinctIndustry":0,"countOfOccurence":1,"countOfOccurenceOfAliases":1,"countOfOccurenceOfNamePreserveList":1,"countOfSignificantStrings":1,"countOfUrlMatch":0,"countryMatchByOverlapScore":0.5,"directCityMatchScore":0.0,"directCountryMatchScore":0.0,"directStateMatchScore":0.0,"exactMatch":false,"fieldMatch":2,"isCommon":false,"isIndustry":false,"isProminent":false,"isProminentByItself":false,"isProminentByParent":false,"isTickerMatch":true,"isUrlMatched":false,"personScore":-1000.0,"stateMatchByOverlapScore":0.0,"sumOfIndustry":0,"w2vScore":0.0,"isGold":0,"isSingleCompany":false}
{"mentionMatched":"daimler","articleId":"33546918980","companyId":"813150","articleLength":6032,"countOfDistinctIndustry":5,"countOfOccurence":1,"countOfOccurenceOfAliases":1,"countOfOccurenceOfNamePreserveList":1,"countOfSignificantStrings":1,"countOfUrlMatch":0,"countryMatchByOverlapScore":0.5,"directCityMatchScore":-1000.0,"directCountryMatchScore":0.6,"directStateMatchScore":-1000.0,"exactMatch":false,"fieldMatch":2,"isCommon":false,"isIndustry":false,"isProminent":false,"isProminentByItself":true,"isProminentByParent":false,"isTickerMatch":true,"isUrlMatched":false,"personScore":0.0,"stateMatchByOverlapScore":-1000.0,"sumOfIndustry":9,"w2vScore":42.2811072625016,"isGold":1,"isSingleCompany":false}
{"mentionMatched":"martech","articleId":"33556114660","companyId":"9635747","articleLength":2550,"countOfDistinctIndustry":8,"countOfOccurence":1,"countOfOccurenceOfAliases":1,"countOfOccurenceOfNamePreserveList":1,"countOfSignificantStrings":1,"countOfUrlMatch":0,"countryMatchByOverlapScore":0.5,"directCityMatchScore":0.0,"directCountryMatchScore":0.0,"directStateMatchScore":0.0,"exactMatch":false,"fieldMatch":2,"isCommon":false,"isIndustry":false,"isProminent":false,"isProminentByItself":false,"isProminentByParent":false,"isTickerMatch":false,"isUrlMatched":false,"personScore":-1000.0,"stateMatchByOverlapScore":0.7,"sumOfIndustry":11,"w2vScore":0.0,"isGold":0,"isSingleCompany":false}
{"mentionMatched":"martech","articleId":"33556114660","companyId":"7872272","articleLength":2550,"countOfDistinctIndustry":32,"countOfOccurence":1,"countOfOccurenceOfAliases":1,"countOfOccurenceOfNamePreserveList":1,"countOfSignificantStrings":1,"countOfUrlMatch":0,"countryMatchByOverlapScore":0.5,"directCityMatchScore":0.0,"directCountryMatchScore":0.0,"directStateMatchScore":0.0,"exactMatch":true,"fieldMatch":3,"isCommon":false,"isIndustry":false,"isProminent":false,"isProminentByItself":false,"isProminentByParent":false,"isTickerMatch":false,"isUrlMatched":false,"personScore":-1000.0,"stateMatchByOverlapScore":0.7,"sumOfIndustry":87,"w2vScore":0.0,"isGold":0,"isSingleCompany":false}
{"mentionMatched":"martech","articleId":"33556114660","companyId":"51811889","articleLength":2550,"countOfDistinctIndustry":0,"countOfOccurence":1,"countOfOccurenceOfAliases":1,"countOfOccurenceOfNamePreserveList":1,"countOfSignificantStrings":1,"countOfUrlMatch":0,"countryMatchByOverlapScore":0.5,"directCityMatchScore":0.0,"directCountryMatchScore":0.0,"directStateMatchScore":-1000.0,"exactMatch":false,"fieldMatch":2,"isCommon":false,"isIndustry":false,"isProminent":false,"isProminentByItself":false,"isProminentByParent":false,"isTickerMatch":false,"isUrlMatched":false,"personScore":-1000.0,"stateMatchByOverlapScore":-1000.0,"sumOfIndustry":0,"w2vScore":0.0,"isGold":0,"isSingleCompany":false}
{"mentionMatched":"martech","articleId":"33556114660","companyId":"8851880","articleLength":2550,"countOfDistinctIndustry":32,"countOfOccurence":1,"countOfOccurenceOfAliases":1,"countOfOccurenceOfNamePreserveList":1,"countOfSignificantStrings":1,"countOfUrlMatch":0,"countryMatchByOverlapScore":0.5,"directCityMatchScore":0.0,"directCountryMatchScore":0.0,"directStateMatchScore":0.0,"exactMatch":false,"fieldMatch":2,"isCommon":false,"isIndustry":false,"isProminent":false,"isProminentByItself":false,"isProminentByParent":false,"isTickerMatch":false,"isUrlMatched":false,"personScore":-1000.0,"stateMatchByOverlapScore":0.7,"sumOfIndustry":87,"w2vScore":0.0,"isGold":0,"isSingleCompany":false}
{"mentionMatched":"martech","articleId":"33556114660","companyId":"10039155","articleLength":2550,"countOfDistinctIndustry":5,"countOfOccurence":1,"countOfOccurenceOfAliases":1,"countOfOccurenceOfNamePreserveList":1,"countOfSignificantStrings":1,"countOfUrlMatch":0,"countryMatchByOverlapScore":0.5,"directCityMatchScore":0.0,"directCountryMatchScore":0.0,"directStateMatchScore":0.0,"exactMatch":false,"fieldMatch":2,"isCommon":false,"isIndustry":false,"isProminent":false,"isProminentByItself":false,"isProminentByParent":false,"isTickerMatch":false,"isUrlMatched":false,"personScore":-1000.0,"stateMatchByOverlapScore":0.7,"sumOfIndustry":5,"w2vScore":0.0,"isGold":0,"isSingleCompany":false}
{"mentionMatched":"martech","articleId":"33556114660","companyId":"1176031","articleLength":2550,"countOfDistinctIndustry":13,"countOfOccurence":1,"countOfOccurenceOfAliases":1,"countOfOccurenceOfNamePreserveList":1,"countOfSignificantStrings":1,"countOfUrlMatch":0,"countryMatchByOverlapScore":0.5,"directCityMatchScore":0.0,"directCountryMatchScore":0.0,"directStateMatchScore":0.0,"exactMatch":false,"fieldMatch":2,"isCommon":false,"isIndustry":false,"isProminent":false,"isProminentByItself":false,"isProminentByParent":false,"isTickerMatch":false,"isUrlMatched":false,"personScore":-1000.0,"stateMatchByOverlapScore":0.7,"sumOfIndustry":45,"w2vScore":0.0,"isGold":0,"isSingleCompany":false}
{"mentionMatched":"martech","articleId":"33556114660","companyId":"51009720","articleLength":2550,"countOfDistinctIndustry":0,"countOfOccurence":1,"countOfOccurenceOfAliases":1,"countOfOccurenceOfNamePreserveList":1,"countOfSignificantStrings":1,"countOfUrlMatch":0,"countryMatchByOverlapScore":0.5,"directCityMatchScore":0.0,"directCountryMatchScore":0.0,"directStateMatchScore":-1000.0,"exactMatch":true,"fieldMatch":3,"isCommon":false,"isIndustry":false,"isProminent":false,"isProminentByItself":false,"isProminentByParent":false,"isTickerMatch":false,"isUrlMatched":false,"personScore":-1000.0,"stateMatchByOverlapScore":-1000.0,"sumOfIndustry":0,"w2vScore":0.0,"isGold":0,"isSingleCompany":false}
{"mentionMatched":"activision blizzard","articleId":"33766091113","companyId":"1496941","articleLength":6912,"countOfDistinctIndustry":10,"countOfOccurence":5,"countOfOccurenceOfAliases":5,"countOfOccurenceOfNamePreserveList":5,"countOfSignificantStrings":5,"countOfUrlMatch":0,"countryMatchByOverlapScore":0.5,"directCityMatchScore":-1000.0,"directCountryMatchScore":0.0,"directStateMatchScore":0.0,"exactMatch":false,"fieldMatch":2,"isCommon":false,"isIndustry":false,"isProminent":false,"isProminentByItself":false,"isProminentByParent":false,"isTickerMatch":true,"isUrlMatched":false,"personScore":-1000.0,"stateMatchByOverlapScore":0.7,"sumOfIndustry":33,"w2vScore":21.80306139370557,"isGold":0,"isSingleCompany":false}
{"mentionMatched":"activision blizzard","articleId":"33766091113","companyId":"726209","articleLength":6912,"countOfDistinctIndustry":13,"countOfOccurence":5,"countOfOccurenceOfAliases":5,"countOfOccurenceOfNamePreserveList":5,"countOfSignificantStrings":5,"countOfUrlMatch":0,"countryMatchByOverlapScore":0.5,"directCityMatchScore":0.0,"directCountryMatchScore":0.0,"directStateMatchScore":0.8,"exactMatch":false,"fieldMatch":2,"isCommon":false,"isIndustry":false,"isProminent":false,"isProminentByItself":true,"isProminentByParent":false,"isTickerMatch":true,"isUrlMatched":false,"personScore":0.0,"stateMatchByOverlapScore":0.7,"sumOfIndustry":69,"w2vScore":21.03868818298632,"isGold":1,"isSingleCompany":false}
{"mentionMatched":"activision blizzard","articleId":"33766091113","companyId":"18553133","articleLength":6912,"countOfDistinctIndustry":0,"countOfOccurence":5,"countOfOccurenceOfAliases":5,"countOfOccurenceOfNamePreserveList":5,"countOfSignificantStrings":5,"countOfUrlMatch":0,"countryMatchByOverlapScore":0.0,"directCityMatchScore":0.0,"directCountryMatchScore":0.6,"directStateMatchScore":-1000.0,"exactMatch":false,"fieldMatch":2,"isCommon":false,"isIndustry":false,"isProminent":false,"isProminentByItself":false,"isProminentByParent":false,"isTickerMatch":true,"isUrlMatched":false,"personScore":-1000.0,"stateMatchByOverlapScore":-1000.0,"sumOfIndustry":0,"w2vScore":0.0,"isGold":0,"isSingleCompany":false}
{"mentionMatched":"activision blizzard","articleId":"33766091113","companyId":"18340384","articleLength":6912,"countOfDistinctIndustry":0,"countOfOccurence":5,"countOfOccurenceOfAliases":5,"countOfOccurenceOfNamePreserveList":5,"countOfSignificantStrings":5,"countOfUrlMatch":0,"countryMatchByOverlapScore":0.5,"directCityMatchScore":0.0,"directCountryMatchScore":0.0,"directStateMatchScore":-1000.0,"exactMatch":true,"fieldMatch":3,"isCommon":false,"isIndustry":false,"isProminent":false,"isProminentByItself":false,"isProminentByParent":false,"isTickerMatch":true,"isUrlMatched":false,"personScore":-1000.0,"stateMatchByOverlapScore":-1000.0,"sumOfIndustry":0,"w2vScore":0.0,"isGold":0,"isSingleCompany":false}
